{
  "trigger": true,
  "modules": [
    "email-filter-allowlist"
  ],
  "parentResource": "elev898a41f87",
  "functionName": "elev898a41f87PreSignup",
  "resourceName": "elev898a41f87PreSignup",
  "parentStack": "auth",
  "triggerEnvs": "[]",
  "triggerDir": "/snapshot/amplify-cli/build/node_modules/@aws-amplify/amplify-category-auth/provider-utils/awscloudformation/triggers/PreSignup",
  "triggerTemplate": "PreSignup.json.ejs",
  "triggerEventPath": "PreSignup.event.json",
  "roleName": "elev898a41f87PreSignup",
  "skipEdit": true,
  "environmentVariableList": [],
  "permissions": {
    "storage": {
      "dynamoDBelev8academy": [
        "read"
      ]
    }
  }
}